tests/__init__.py
tests/conftest.py
tests/integration/__init__.py
tests/integration/test_end_to_end.py
tests/unit/__init__.py
tests/unit/test_ai_processor.py
tests/unit/test_transcript_generator.py
tests/unit/test_youtube_client.py
youtube_transcript_generator/__init__.py
youtube_transcript_generator/config.py
youtube_transcript_generator/exceptions.py
youtube_transcript_generator/logger.py
youtube_transcript_generator/ai/__init__.py
youtube_transcript_generator/ai/base_processor.py
youtube_transcript_generator/ai/gemini_processor.py
youtube_transcript_generator/cli/__init__.py
youtube_transcript_generator/cli/main.py
youtube_transcript_generator/core/__init__.py
youtube_transcript_generator/core/models.py
youtube_transcript_generator/core/transcript_generator.py
youtube_transcript_generator/core/youtube_client.py
youtube_transcript_generator/utils/__init__.py
youtube_transcript_generator/utils/helpers.py
youtube_transcript_generator/utils/validators.py
youtube_transcript_generator-0.1.1.dist-info/METADATA
youtube_transcript_generator-0.1.1.dist-info/WHEEL
youtube_transcript_generator-0.1.1.dist-info/entry_points.txt
youtube_transcript_generator-0.1.1.dist-info/top_level.txt
youtube_transcript_generator-0.1.1.dist-info/RECORD
