Metadata-Version: 2.2
Name: youtube-transcript-generator
Version: 0.1.1
Summary: A Python package to generate AI-powered transcripts from YouTube videos
Author-email: Manoj Tyagi <tyagimanojtyagi.22@gmail.com>
License: MIT
Project-URL: Homepage, https://github.com/thewolfcommander/pulse__youtube-transcript
Project-URL: Documentation, https://github.com/thewolfcommander/pulse__youtube-transcript/docs
Project-URL: Repository, https://github.com/thewolfcommander/pulse__youtube-transcript.git
Project-URL: Issues, https://github.com/thewolfcommander/pulse__youtube-transcript/issues
Classifier: Development Status :: 3 - Alpha
Classifier: Intended Audience :: Developers
Classifier: License :: OSI Approved :: MIT License
Classifier: Programming Language :: Python :: 3
Classifier: Programming Language :: Python :: 3.8
Classifier: Programming Language :: Python :: 3.9
Classifier: Programming Language :: Python :: 3.10
Classifier: Programming Language :: Python :: 3.11
Classifier: Topic :: Multimedia :: Video
Classifier: Topic :: Text Processing
Requires-Python: >=3.11
Requires-Dist: google-generativeai>=0.3.0
Requires-Dist: yt-dlp>=2024.1.1
Requires-Dist: pydantic>=2.6.0
Requires-Dist: pydantic-settings>=2.1.0
Requires-Dist: typer[all]>=0.9.0
Requires-Dist: rich>=13.7.0
Requires-Dist: loguru>=0.7.2
Requires-Dist: aiohttp>=3.9.1
Requires-Dist: python-dotenv>=1.0.0
Requires-Dist: asyncio>=3.4.3
Provides-Extra: dev
Requires-Dist: pytest>=8.0.0; extra == "dev"
Requires-Dist: pytest-asyncio>=0.23.5; extra == "dev"
Requires-Dist: pytest-cov>=4.1.0; extra == "dev"
Requires-Dist: black>=24.1.0; extra == "dev"
Requires-Dist: isort>=5.13.2; extra == "dev"
Requires-Dist: mypy>=1.8.0; extra == "dev"
Requires-Dist: pylint>=3.0.3; extra == "dev"
Requires-Dist: pre-commit>=3.6.0; extra == "dev"
Provides-Extra: interactive
Requires-Dist: ipython>=8.12.0; extra == "interactive"
Requires-Dist: pytest-watch>=4.2.0; extra == "interactive"
Dynamic: requires-python
